{
  "hashes/2G_VALQUIRIA_consolidated.hc22000": {
    "path": "hashes/2G_VALQUIRIA_consolidated.hc22000",
    "name": "2G_VALQUIRIA_consolidated.hc22000",
    "essid": "2G_VALQUIRIA_consolidated",
    "network_bssid": "34:49:5B:87:AE:63",
    "hash_mode": "22000",
    "size": 96,
    "size_human": "96.0 B",
    "timestamp": "2026-01-18T01:04:37.168019",
    "cracked": true,
    "cracked_password": "17031962",
    "cracked_hex": "3137303331393632",
    "cracked_salt": "56015090",
    "cracked_output": "/home/kozi/sniff/cracked/2G_VALQUIRIA_consolidated__mask_8digit__20260118_024425.cracked",
    "cracked_at": "2026-01-18T02:46:56.167217",
    "cracking_attempts": []
  },
  "hashes/2_4G_Inpelve_consolidated.hc22000": {
    "path": "hashes/2_4G_Inpelve_consolidated.hc22000",
    "name": "2_4G_Inpelve_consolidated.hc22000",
    "essid": "2_4G_Inpelve_consolidated",
    "network_bssid": "8C:44:4F:02:C1:80",
    "hash_mode": "22000",
    "size": 96,
    "size_human": "96.0 B",
    "timestamp": "2026-01-18T01:04:37.167757",
    "cracked": false,
    "cracked_password": null,
    "cracked_hex": null,
    "cracked_salt": null,
    "cracked_output": null,
    "cracked_at": null,
    "cracking_attempts": [
      {
        "wordlist": "__MASK_8DIGIT__",
        "rule": ""
      }
    ]
  },
  "hashes/508_-_Castillo_Saude_e_Estetica_consolidated.hc22000": {
    "path": "hashes/508_-_Castillo_Saude_e_Estetica_consolidated.hc22000",
    "name": "508_-_Castillo_Saude_e_Estetica_consolidated.hc22000",
    "essid": "508_-_Castillo_Saude_e_Estetica_consolidated",
    "network_bssid": "68:E1:66:63:E4:B9",
    "hash_mode": "22000",
    "size": 904,
    "size_human": "904.0 B",
    "timestamp": "2026-01-18T01:04:37.169415",
    "cracked": false,
    "cracked_password": null,
    "cracked_hex": null,
    "cracked_salt": null,
    "cracked_output": null,
    "cracked_at": null,
    "cracking_attempts": [
      {
        "wordlist": "__MASK_8DIGIT__",
        "rule": ""
      }
    ]
  },
  "hashes/5G_JULIA_consolidated.hc22000": {
    "path": "hashes/5G_JULIA_consolidated.hc22000",
    "name": "5G_JULIA_consolidated.hc22000",
    "essid": "5G_JULIA_consolidated",
    "network_bssid": "8C:44:4F:B3:E1:7D",
    "hash_mode": "22000",
    "size": 88,
    "size_human": "88.0 B",
    "timestamp": "2026-01-18T01:04:37.168479",
    "cracked": false,
    "cracked_password": null,
    "cracked_hex": null,
    "cracked_salt": null,
    "cracked_output": null,
    "cracked_at": null,
    "cracking_attempts": [
      {
        "wordlist": "__MASK_8DIGIT__",
        "rule": ""
      }
    ]
  },
  "hashes/74_B_2G_consolidated.hc22000": {
    "path": "hashes/74_B_2G_consolidated.hc22000",
    "name": "74_B_2G_consolidated.hc22000",
    "essid": "74_B_2G_consolidated",
    "network_bssid": "84:01:12:60:7B:3C",
    "hash_mode": "22000",
    "size": 1042,
    "size_human": "1.0 KB",
    "timestamp": "2026-01-18T01:04:37.169192",
    "cracked": true,
    "cracked_password": "12515621",
    "cracked_hex": null,
    "cracked_salt": null,
    "cracked_output": null,
    "cracked_at": "2026-01-18T01:10:39.725152",
    "cracking_attempts": []
  },
  "hashes/74_B_5G_consolidated.hc22000": {
    "path": "hashes/74_B_5G_consolidated.hc22000",
    "name": "74_B_5G_consolidated.hc22000",
    "essid": "74_B_5G_consolidated",
    "network_bssid": "84:01:12:60:7B:3D",
    "hash_mode": "22000",
    "size": 86,
    "size_human": "86.0 B",
    "timestamp": "2026-01-18T01:04:37.168801",
    "cracked": true,
    "cracked_password": null,
    "cracked_hex": null,
    "cracked_salt": null,
    "cracked_output": null,
    "cracked_at": "2026-01-18T01:10:39.725320",
    "cracking_attempts": []
  },
  "hashes/AML_consolidated.hc22000": {
    "path": "hashes/AML_consolidated.hc22000",
    "name": "AML_consolidated.hc22000",
    "essid": "AML_consolidated",
    "network_bssid": "34:49:5B:96:02:70",
    "hash_mode": "22000",
    "size": 156,
    "size_human": "156.0 B",
    "timestamp": "2026-01-18T01:04:37.168076",
    "cracked": false,
    "cracked_password": null,
    "cracked_hex": null,
    "cracked_salt": null,
    "cracked_output": null,
    "cracked_at": null,
    "cracking_attempts": [
      {
        "wordlist": "__MASK_8DIGIT__",
        "rule": ""
      }
    ]
  },
  "hashes/APT22_consolidated.hc22000": {
    "path": "hashes/APT22_consolidated.hc22000",
    "name": "APT22_consolidated.hc22000",
    "essid": "APT22_consolidated",
    "network_bssid": "74:3A:EF:5F:48:13",
    "hash_mode": "22000",
    "size": 82,
    "size_human": "82.0 B",
    "timestamp": "2026-01-18T01:04:37.169363",
    "cracked": true,
    "cracked_password": "26262323",
    "cracked_hex": null,
    "cracked_salt": null,
    "cracked_output": null,
    "cracked_at": "2026-01-18T01:10:39.725598",
    "cracking_attempts": []
  },
  "hashes/CLARO_2G834AB4_consolidated.hc22000": {
    "path": "hashes/CLARO_2G834AB4_consolidated.hc22000",
    "name": "CLARO_2G834AB4_consolidated.hc22000",
    "essid": "CLARO_2G834AB4_consolidated",
    "network_bssid": "84:01:12:83:4A:B9",
    "hash_mode": "22000",
    "size": 200,
    "size_human": "200.0 B",
    "timestamp": "2026-01-18T01:04:37.169248",
    "cracked": false,
    "cracked_password": null,
    "cracked_hex": null,
    "cracked_salt": null,
    "cracked_output": null,
    "cracked_at": null,
    "cracking_attempts": [
      {
        "wordlist": "__MASK_8DIGIT__",
        "rule": ""
      }
    ]
  },
  "hashes/CLARO_5896B_consolidated.hc22000": {
    "path": "hashes/CLARO_5896B_consolidated.hc22000",
    "name": "CLARO_5896B_consolidated.hc22000",
    "essid": "CLARO_5896B_consolidated",
    "network_bssid": "00:0D:F2:BC:A9:05",
    "hash_mode": "22000",
    "size": 412,
    "size_human": "412.0 B",
    "timestamp": "2026-01-18T01:04:37.167696",
    "cracked": true,
    "cracked_password": "12345678",
    "cracked_hex": "3132333435363738",
    "cracked_salt": "0",
    "cracked_output": "/home/kozi/sniff/cracked/CLARO_5896B_consolidated__mask_8digit__20260118_030452.cracked",
    "cracked_at": "2026-01-18T03:04:55.903022",
    "cracking_attempts": []
  },
  "hashes/CLARO_6084B1-5G-BH_consolidated.hc22000": {
    "path": "hashes/CLARO_6084B1-5G-BH_consolidated.hc22000",
    "name": "CLARO_6084B1-5G-BH_consolidated.hc22000",
    "essid": "CLARO_6084B1-5G-BH_consolidated",
    "network_bssid": "DA:CF:61:60:85:B2",
    "hash_mode": "22000",
    "size": 1242,
    "size_human": "1.2 KB",
    "timestamp": "2026-01-18T01:04:37.168634",
    "cracked": false,
    "cracked_password": null,
    "cracked_hex": null,
    "cracked_salt": null,
    "cracked_output": null,
    "cracked_at": null,
    "cracking_attempts": [
      {
        "wordlist": "__MASK_8DIGIT__",
        "rule": ""
      }
    ]
  },
  "hashes/CLEIDE_consolidated.hc22000": {
    "path": "hashes/CLEIDE_consolidated.hc22000",
    "name": "CLEIDE_consolidated.hc22000",
    "essid": "CLEIDE_consolidated",
    "network_bssid": "54:A6:5C:8E:7F:29",
    "hash_mode": "22000",
    "size": 474,
    "size_human": "474.0 B",
    "timestamp": "2026-01-18T01:04:37.168417",
    "cracked": true,
    "cracked_password": "",
    "cracked_hex": null,
    "cracked_salt": null,
    "cracked_output": null,
    "cracked_at": "2026-01-18T01:11:07.555247",
    "cracking_attempts": []
  },
  "hashes/DENTISTAS_508_consolidated.hc22000": {
    "path": "hashes/DENTISTAS_508_consolidated.hc22000",
    "name": "DENTISTAS_508_consolidated.hc22000",
    "essid": "DENTISTAS_508_consolidated",
    "network_bssid": "D0:57:94:75:75:2D",
    "hash_mode": "22000",
    "size": 294,
    "size_human": "294.0 B",
    "timestamp": "2026-01-18T01:04:37.168243",
    "cracked": false,
    "cracked_password": null,
    "cracked_hex": null,
    "cracked_salt": null,
    "cracked_output": null,
    "cracked_at": null,
    "cracking_attempts": [
      {
        "wordlist": "__MASK_8DIGIT__",
        "rule": ""
      }
    ]
  },
  "hashes/FAMILIAPS_consolidated.hc22000": {
    "path": "hashes/FAMILIAPS_consolidated.hc22000",
    "name": "FAMILIAPS_consolidated.hc22000",
    "essid": "FAMILIAPS_consolidated",
    "network_bssid": "44:89:6D:4E:5A:6F",
    "hash_mode": "22000",
    "size": 396,
    "size_human": "396.0 B",
    "timestamp": "2026-01-18T01:04:37.168187",
    "cracked": false,
    "cracked_password": null,
    "cracked_hex": null,
    "cracked_salt": null,
    "cracked_output": null,
    "cracked_at": null,
    "cracking_attempts": [
      {
        "wordlist": "__MASK_8DIGIT__",
        "rule": ""
      }
    ]
  },
  "hashes/Florival_consolidated.hc22000": {
    "path": "hashes/Florival_consolidated.hc22000",
    "name": "Florival_consolidated.hc22000",
    "essid": "Florival_consolidated",
    "network_bssid": "28:32:C5:88:B9:68",
    "hash_mode": "22000",
    "size": 176,
    "size_human": "176.0 B",
    "timestamp": "2026-01-18T01:04:37.168972",
    "cracked": true,
    "cracked_password": "15061938",
    "cracked_hex": "3135303631393338",
    "cracked_salt": "88004050",
    "cracked_output": "/home/kozi/sniff/cracked/Florival_consolidated__mask_8digit__20260118_015110.cracked",
    "cracked_at": "2026-01-18T01:54:57.330572",
    "cracking_attempts": []
  },
  "hashes/GARCIA_MARIANO_ADVOGADOS_2G_consolidated.hc22000": {
    "path": "hashes/GARCIA_MARIANO_ADVOGADOS_2G_consolidated.hc22000",
    "name": "GARCIA_MARIANO_ADVOGADOS_2G_consolidated.hc22000",
    "essid": "GARCIA_MARIANO_ADVOGADOS_2G_consolidated",
    "network_bssid": "5C:76:95:96:19:25",
    "hash_mode": "22000",
    "size": 126,
    "size_human": "126.0 B",
    "timestamp": "2026-01-18T01:04:37.167812",
    "cracked": false,
    "cracked_password": null,
    "cracked_hex": null,
    "cracked_salt": null,
    "cracked_output": null,
    "cracked_at": null,
    "cracking_attempts": [
      {
        "wordlist": "__MASK_8DIGIT__",
        "rule": ""
      }
    ]
  },
  "hashes/IVONE_2G_consolidated.hc22000": {
    "path": "hashes/IVONE_2G_consolidated.hc22000",
    "name": "IVONE_2G_consolidated.hc22000",
    "essid": "IVONE_2G_consolidated",
    "network_bssid": "18:34:AF:29:BC:69",
    "hash_mode": "22000",
    "size": 746,
    "size_human": "746.0 B",
    "timestamp": "2026-01-18T01:04:37.169133",
    "cracked": true,
    "cracked_password": "20938722",
    "cracked_hex": null,
    "cracked_salt": null,
    "cracked_output": null,
    "cracked_at": "2026-01-18T01:10:39.727421",
    "cracking_attempts": []
  },
  "hashes/IVONE_5G_consolidated.hc22000": {
    "path": "hashes/IVONE_5G_consolidated.hc22000",
    "name": "IVONE_5G_consolidated.hc22000",
    "essid": "IVONE_5G_consolidated",
    "network_bssid": "18:34:AF:29:BC:6A",
    "hash_mode": "22000",
    "size": 88,
    "size_human": "88.0 B",
    "timestamp": "2026-01-18T01:04:37.168361",
    "cracked": true,
    "cracked_password": "",
    "cracked_hex": null,
    "cracked_salt": null,
    "cracked_output": null,
    "cracked_at": "2026-01-18T01:10:58.616683",
    "cracking_attempts": []
  },
  "hashes/LUCAS84B_5G_consolidated.hc22000": {
    "path": "hashes/LUCAS84B_5G_consolidated.hc22000",
    "name": "LUCAS84B_5G_consolidated.hc22000",
    "essid": "LUCAS84B_5G_consolidated",
    "network_bssid": "68:02:B8:F9:2B:59",
    "hash_mode": "22000",
    "size": 800,
    "size_human": "800.0 B",
    "timestamp": "2026-01-18T01:04:37.169306",
    "cracked": false,
    "cracked_password": null,
    "cracked_hex": null,
    "cracked_salt": null,
    "cracked_output": null,
    "cracked_at": null,
    "cracking_attempts": [
      {
        "wordlist": "__MASK_8DIGIT__",
        "rule": ""
      }
    ]
  },
  "hashes/MALU-5G_consolidated.hc22000": {
    "path": "hashes/MALU-5G_consolidated.hc22000",
    "name": "MALU-5G_consolidated.hc22000",
    "essid": "MALU-5G_consolidated",
    "network_bssid": "D8:C6:78:D2:60:CF",
    "hash_mode": "22000",
    "size": 784,
    "size_human": "784.0 B",
    "timestamp": "2026-01-18T01:04:37.168132",
    "cracked": false,
    "cracked_password": null,
    "cracked_hex": null,
    "cracked_salt": null,
    "cracked_output": null,
    "cracked_at": null,
    "cracking_attempts": [
      {
        "wordlist": "__MASK_8DIGIT__",
        "rule": ""
      }
    ]
  },
  "hashes/MBi_nezi_consolidated.hc22000": {
    "path": "hashes/MBi_nezi_consolidated.hc22000",
    "name": "MBi_nezi_consolidated.hc22000",
    "essid": "MBi_nezi_consolidated",
    "network_bssid": "84:01:12:E9:A4:41",
    "hash_mode": "22000",
    "size": 88,
    "size_human": "88.0 B",
    "timestamp": "2026-01-18T01:04:37.168579",
    "cracked": true,
    "cracked_password": "19811956",
    "cracked_hex": "3139383131393536",
    "cracked_salt": "17023330",
    "cracked_output": "/home/kozi/sniff/cracked/MBi_nezi_consolidated__mask_8digit__20260118_021642.cracked",
    "cracked_at": "2026-01-18T02:17:30.862870",
    "cracking_attempts": []
  },
  "hashes/Mari-5G_consolidated.hc22000": {
    "path": "hashes/Mari-5G_consolidated.hc22000",
    "name": "Mari-5G_consolidated.hc22000",
    "essid": "Mari-5G_consolidated",
    "network_bssid": "68:E1:66:63:E4:C1",
    "hash_mode": "22000",
    "size": 392,
    "size_human": "392.0 B",
    "timestamp": "2026-01-18T01:04:37.167867",
    "cracked": true,
    "cracked_password": "12345678",
    "cracked_hex": "3132333435363738",
    "cracked_salt": "0",
    "cracked_output": "/home/kozi/sniff/cracked/Mari-5G_consolidated__mask_8digit__20260118_025552.cracked",
    "cracked_at": "2026-01-18T02:55:55.315018",
    "cracking_attempts": []
  },
  "hashes/NET_2G11266B_consolidated.hc22000": {
    "path": "hashes/NET_2G11266B_consolidated.hc22000",
    "name": "NET_2G11266B_consolidated.hc22000",
    "essid": "NET_2G11266B_consolidated",
    "network_bssid": "10:C2:5A:11:26:70",
    "hash_mode": "22000",
    "size": 2310,
    "size_human": "2.3 KB",
    "timestamp": "2026-01-18T01:04:37.168858",
    "cracked": false,
    "cracked_password": null,
    "cracked_hex": null,
    "cracked_salt": null,
    "cracked_output": null,
    "cracked_at": null,
    "cracking_attempts": [
      {
        "wordlist": "__MASK_8DIGIT__",
        "rule": ""
      }
    ]
  },
  "hashes/NET_2GE39300_consolidated.hc22000": {
    "path": "hashes/NET_2GE39300_consolidated.hc22000",
    "name": "NET_2GE39300_consolidated.hc22000",
    "essid": "NET_2GE39300_consolidated",
    "network_bssid": "A4:56:CC:E3:93:05",
    "hash_mode": "22000",
    "size": 192,
    "size_human": "192.0 B",
    "timestamp": "2026-01-18T01:04:37.168532",
    "cracked": false,
    "cracked_password": null,
    "cracked_hex": null,
    "cracked_salt": null,
    "cracked_output": null,
    "cracked_at": null,
    "cracking_attempts": [
      {
        "wordlist": "__MASK_8DIGIT__",
        "rule": ""
      }
    ]
  },
  "hashes/Nilza_2G_consolidated.hc22000": {
    "path": "hashes/Nilza_2G_consolidated.hc22000",
    "name": "Nilza_2G_consolidated.hc22000",
    "essid": "Nilza_2G_consolidated",
    "network_bssid": "68:02:B8:AE:62:07",
    "hash_mode": "22000",
    "size": 394,
    "size_human": "394.0 B",
    "timestamp": "2026-01-18T01:04:37.169464",
    "cracked": false,
    "cracked_password": null,
    "cracked_hex": null,
    "cracked_salt": null,
    "cracked_output": null,
    "cracked_at": null,
    "cracking_attempts": [
      {
        "wordlist": "__MASK_8DIGIT__",
        "rule": ""
      }
    ]
  },
  "hashes/Ordones_consolidated.hc22000": {
    "path": "hashes/Ordones_consolidated.hc22000",
    "name": "Ordones_consolidated.hc22000",
    "essid": "Ordones_consolidated",
    "network_bssid": "10:72:23:B1:95:9F",
    "hash_mode": "22000",
    "size": 478,
    "size_human": "478.0 B",
    "timestamp": "2026-01-18T01:04:37.168302",
    "cracked": true,
    "cracked_password": null,
    "cracked_hex": null,
    "cracked_salt": null,
    "cracked_output": null,
    "cracked_at": "2026-01-18T01:10:39.728816",
    "cracking_attempts": []
  },
  "hashes/PerguntenoChatGPT_consolidated.hc22000": {
    "path": "hashes/PerguntenoChatGPT_consolidated.hc22000",
    "name": "PerguntenoChatGPT_consolidated.hc22000",
    "essid": "PerguntenoChatGPT_consolidated",
    "network_bssid": "84:01:12:DF:5A:14",
    "hash_mode": "22000",
    "size": 106,
    "size_human": "106.0 B",
    "timestamp": "2026-01-18T01:04:37.169078",
    "cracked": false,
    "cracked_password": null,
    "cracked_hex": null,
    "cracked_salt": null,
    "cracked_output": null,
    "cracked_at": null,
    "cracking_attempts": [
      {
        "wordlist": "__MASK_8DIGIT__",
        "rule": ""
      }
    ]
  },
  "hashes/Sonia_11C-2G_consolidated.hc22000": {
    "path": "hashes/Sonia_11C-2G_consolidated.hc22000",
    "name": "Sonia_11C-2G_consolidated.hc22000",
    "essid": "Sonia_11C-2G_consolidated",
    "network_bssid": "84:01:12:DB:4C:BD",
    "hash_mode": "22000",
    "size": 288,
    "size_human": "288.0 B",
    "timestamp": "2026-01-18T01:04:37.167968",
    "cracked": false,
    "cracked_password": null,
    "cracked_hex": null,
    "cracked_salt": null,
    "cracked_output": null,
    "cracked_at": null,
    "cracking_attempts": [
      {
        "wordlist": "__MASK_8DIGIT__",
        "rule": ""
      }
    ]
  },
  "hashes/Sonia_11C-5G_consolidated.hc22000": {
    "path": "hashes/Sonia_11C-5G_consolidated.hc22000",
    "name": "Sonia_11C-5G_consolidated.hc22000",
    "essid": "Sonia_11C-5G_consolidated",
    "network_bssid": "84:01:12:DB:4C:BE",
    "hash_mode": "22000",
    "size": 96,
    "size_human": "96.0 B",
    "timestamp": "2026-01-18T01:04:37.167918",
    "cracked": false,
    "cracked_password": null,
    "cracked_hex": null,
    "cracked_salt": null,
    "cracked_output": null,
    "cracked_at": null,
    "cracking_attempts": [
      {
        "wordlist": "__MASK_8DIGIT__",
        "rule": ""
      }
    ]
  },
  "hashes/VISITANTE_2_4G_consolidated.hc22000": {
    "path": "hashes/VISITANTE_2_4G_consolidated.hc22000",
    "name": "VISITANTE_2_4G_consolidated.hc22000",
    "essid": "VISITANTE_2_4G_consolidated",
    "network_bssid": "54:A6:5C:10:0A:28",
    "hash_mode": "22000",
    "size": 200,
    "size_human": "200.0 B",
    "timestamp": "2026-01-18T01:04:37.168691",
    "cracked": false,
    "cracked_password": null,
    "cracked_hex": null,
    "cracked_salt": null,
    "cracked_output": null,
    "cracked_at": null,
    "cracking_attempts": [
      {
        "wordlist": "__MASK_8DIGIT__",
        "rule": ""
      }
    ]
  },
  "hashes/Zain_5G_consolidated.hc22000": {
    "path": "hashes/Zain_5G_consolidated.hc22000",
    "name": "Zain_5G_consolidated.hc22000",
    "essid": "Zain_5G_consolidated",
    "network_bssid": "8C:44:4F:49:06:E4",
    "hash_mode": "22000",
    "size": 172,
    "size_human": "172.0 B",
    "timestamp": "2026-01-18T01:04:37.168745",
    "cracked": false,
    "cracked_password": null,
    "cracked_hex": null,
    "cracked_salt": null,
    "cracked_output": null,
    "cracked_at": null,
    "cracking_attempts": [
      {
        "wordlist": "__MASK_8DIGIT__",
        "rule": ""
      }
    ]
  },
  "hashes/Zen_consolidated.hc22000": {
    "path": "hashes/Zen_consolidated.hc22000",
    "name": "Zen_consolidated.hc22000",
    "essid": "Zen_consolidated",
    "network_bssid": "02:EB:D8:8B:52:3C",
    "hash_mode": "22000",
    "size": 1548,
    "size_human": "1.5 KB",
    "timestamp": "2026-01-18T01:04:37.169027",
    "cracked": true,
    "cracked_password": "zenwifi64",
    "cracked_hex": null,
    "cracked_salt": null,
    "cracked_output": null,
    "cracked_at": "2026-01-18T01:10:39.729642",
    "cracking_attempts": []
  },
  "hashes/moduletest_consolidated.hc22000": {
    "path": "hashes/moduletest_consolidated.hc22000",
    "name": "moduletest_consolidated.hc22000",
    "essid": "moduletest_consolidated",
    "network_bssid": "68:E1:66:63:E4:BD",
    "hash_mode": "22000",
    "size": 796,
    "size_human": "796.0 B",
    "timestamp": "2026-01-18T01:04:37.168915",
    "cracked": false,
    "cracked_password": null,
    "cracked_hex": null,
    "cracked_salt": null,
    "cracked_output": null,
    "cracked_at": null,
    "cracking_attempts": [
      {
        "wordlist": "__MASK_8DIGIT__",
        "rule": ""
      }
    ]
  }
}